{
    "posts": [
        {
            "id": "123e4567-e89b-12d3-a456-426614174000",
            "title": "Post 1",
            "description": "Got first post",
            "imageUrl": "https://picsum.photos/200"
        },
        {
            "id": "223e4567-e89b-12d3-a456-426614174001",
            "title": "Post 2",
            "description": "Excited for the second post!",
            "imageUrl": "https://picsum.photos/200"
        },
        {
            "id": "323e4567-e89b-12d3-a456-426614174002",
            "title": "Post 3",
            "description": "Third post vibes",
            "imageUrl": "https://picsum.photos/200"
        },
        {
            "id": "423e4567-e89b-12d3-a456-426614174003",
            "title": "Post 4",
            "description": "Another day, another post",
            "imageUrl": "https://picsum.photos/200"
        },
        {
            "id": "523e4567-e89b-12d3-a456-426614174004",
            "title": "Post 5",
            "description": "Loving this journey",
            "imageUrl": "https://picsum.photos/200"
        },
        {
            "id": "623e4567-e89b-12d3-a456-426614174005",
            "title": "Post 6",
            "description": "Halfway through!",
            "imageUrl": "https://picsum.photos/200"
        },
        {
            "id": "723e4567-e89b-12d3-a456-426614174006",
            "title": "Post 7",
            "description": "Lucky number seven",
            "imageUrl": "https://picsum.photos/200"
        },
        {
            "id": "823e4567-e89b-12d3-a456-426614174007",
            "title": "Post 8",
            "description": "Keeping it real",
            "imageUrl": "https://picsum.photos/200"
        },
        {
            "id": "923e4567-e89b-12d3-a456-426614174008",
            "title": "Post 9",
            "description": "Almost at double digits",
            "imageUrl": "https://picsum.photos/200"
        },
        {
            "id": "a23e4567-e89b-12d3-a456-426614174009",
            "title": "Post 10",
            "description": "Made it to ten!",
            "imageUrl": "https://picsum.photos/200"
        }
    ],
    "hasMore": true
}
